{"id": "article_11", "sentences": [{"article": "article_11", "id": "sent_91", "position_in_article": 0, "content": "Seoul refuses to recognize Russia's Crimea annexation", "subjectivity": {"score": {"avg": 0.2, "maj": 0.0, "intensified": 0.0}, "judgements": [0.0, 0.0, 1.0, 0.0, 0.0], "cw_origins": ["VEN", "VEN", "USA", "VEN", "TUR"]}, "hidden_assumptions": {"score": {"avg": 0.6, "maj": 0.0, "intensified": 0.0}, "judgements": [0.0, 0.0, 0.0, 1.0, 2.0], "cw_origins": ["USA", "USA", "USA", "BIH", "EGY"]}, "framing": {"score": {"russia": {"avg": 0.0, "maj": 0.0, "intensified": 0.0}, "ukraine": {"avg": 0.0, "maj": 0.0, "intensified": 0.0}, "west": {"avg": 0.0, "maj": 0.0, "intensified": 0.0}}, "judgements": {"russia": [0.0, 0.0, 0.0, 0.0, 0.0], "ukraine": [0.0, 0.0, 0.0, 0.0, 0.0], "west": [0.0, 0.0, 0.0, 0.0, 0.0]}, "cw_origins": ["VEN", "VEN", "USA", "VEN", "COL"]}, "bias": {"score": {"pro-russia": {"avg": 0.9333333333333333, "maj": 1.0, "intensified": 1.0}, "pro-west": {"avg": 0.9333333333333333, "maj": 1.0, "intensified": 1.0}}, "judgements": {"pro-russia": [1.0, 1.0, 1.0, 1.0, 1.0, 1.0, 1.0, 1.0, 0.0, 1.0, 1.0, 1.0, 1.0, 1.0, 1.0], "pro-west": [1.0, 1.0, 1.0, 1.0, 1.0, 1.0, 1.0, 1.0, 0.0, 1.0, 1.0, 1.0, 1.0, 1.0, 1.0]}, "cw_origins": ["VEN", "USA", "VEN", "VEN", "VEN", "USA", "VEN", "VEN", "USA", "VEN", "USA", "VEN", "VEN", "VEN", "USA"]}}, {"article": "article_11", "id": "sent_92", "position_in_article": 1, "content": "South Korea does not recognize Russia\u2019s move to annex Crimea, the Foreign Ministry said Wednesday, joining some Western countries\u2019 denouncement of Russian President Vladimir Putin\u2019s takeover of the previous Ukrainian territory.", "subjectivity": {"score": {"avg": 0.8, "maj": 0.0, "intensified": 0.0}, "judgements": [0.0, 0.0, 1.0, 0.0, 3.0], "cw_origins": ["VEN", "VEN", "USA", "VEN", "TUR"]}, "hidden_assumptions": {"score": {"avg": 0.6, "maj": 0.0, "intensified": 0.0}, "judgements": [0.0, 0.0, 0.0, 1.0, 2.0], "cw_origins": ["USA", "USA", "USA", "BIH", "EGY"]}, "framing": {"score": {"russia": {"avg": 0.0, "maj": 0.0, "intensified": 0.0}, "ukraine": {"avg": 0.0, "maj": 0.0, "intensified": 0.0}, "west": {"avg": 0.0, "maj": 0.0, "intensified": 0.0}}, "judgements": {"russia": [0.0, 0.0, 0.0, 0.0, 0.0], "ukraine": [0.0, 0.0, 0.0, 0.0, 0.0], "west": [0.0, 0.0, 0.0, 0.0, 0.0]}, "cw_origins": ["VEN", "VEN", "USA", "VEN", "COL"]}, "bias": {"score": {"pro-russia": {"avg": 0.9333333333333333, "maj": 1.0, "intensified": 1.0}, "pro-west": {"avg": 0.9333333333333333, "maj": 1.0, "intensified": 1.0}}, "judgements": {"pro-russia": [1.0, 1.0, 1.0, 1.0, 1.0, 1.0, 1.0, 1.0, 0.0, 1.0, 1.0, 1.0, 1.0, 1.0, 1.0], "pro-west": [1.0, 1.0, 1.0, 1.0, 1.0, 1.0, 1.0, 1.0, 0.0, 1.0, 1.0, 1.0, 1.0, 1.0, 1.0]}, "cw_origins": ["VEN", "USA", "VEN", "VEN", "VEN", "USA", "VEN", "VEN", "USA", "VEN", "USA", "VEN", "VEN", "VEN", "USA"]}}, {"article": "article_11", "id": "sent_93", "position_in_article": 2, "content": "On Tuesday, Putin signed a treaty of accession with new leaders of Crimea, making the southern region of Ukraine a territory of Russia.", "subjectivity": {"score": {"avg": 0.4, "maj": 0.0, "intensified": 0.0}, "judgements": [0.0, 0.0, 1.0, 0.0, 1.0], "cw_origins": ["VEN", "VEN", "USA", "VEN", "TUR"]}, "hidden_assumptions": {"score": {"avg": 0.6, "maj": 0.0, "intensified": 0.0}, "judgements": [0.0, 0.0, 0.0, 1.0, 2.0], "cw_origins": ["USA", "USA", "USA", "BIH", "EGY"]}, "framing": {"score": {"russia": {"avg": 0.0, "maj": 0.0, "intensified": 0.0}, "ukraine": {"avg": 0.0, "maj": 0.0, "intensified": 0.0}, "west": {"avg": 0.0, "maj": 0.0, "intensified": 0.0}}, "judgements": {"russia": [0.0, 0.0, 0.0, 0.0, 0.0], "ukraine": [0.0, 0.0, 0.0, 0.0, 0.0], "west": [0.0, 0.0, 0.0, 0.0, 0.0]}, "cw_origins": ["VEN", "VEN", "USA", "VEN", "COL"]}, "bias": {"score": {"pro-russia": {"avg": 0.9333333333333333, "maj": 1.0, "intensified": 1.0}, "pro-west": {"avg": 0.9333333333333333, "maj": 1.0, "intensified": 1.0}}, "judgements": {"pro-russia": [1.0, 1.0, 1.0, 1.0, 1.0, 1.0, 1.0, 1.0, 0.0, 1.0, 1.0, 1.0, 1.0, 1.0, 1.0], "pro-west": [1.0, 1.0, 1.0, 1.0, 1.0, 1.0, 1.0, 1.0, 0.0, 1.0, 1.0, 1.0, 1.0, 1.0, 1.0]}, "cw_origins": ["VEN", "USA", "VEN", "VEN", "VEN", "USA", "VEN", "VEN", "USA", "VEN", "USA", "VEN", "VEN", "VEN", "USA"]}}, {"article": "article_11", "id": "sent_94", "position_in_article": 3, "content": "The takeover took place as political instability continued in Crimea after the collapse late last month of Ukraine\u2019s previous Viktor Yanukovych government.", "subjectivity": {"score": {"avg": 0.2, "maj": 0.0, "intensified": 0.0}, "judgements": [0.0, 0.0, 1.0, 0.0, 0.0], "cw_origins": ["VEN", "VEN", "USA", "VEN", "TUR"]}, "hidden_assumptions": {"score": {"avg": 0.6, "maj": 0.0, "intensified": 0.0}, "judgements": [0.0, 0.0, 0.0, 1.0, 2.0], "cw_origins": ["USA", "USA", "USA", "BIH", "EGY"]}, "framing": {"score": {"russia": {"avg": 0.0, "maj": 0.0, "intensified": 0.0}, "ukraine": {"avg": 0.0, "maj": 0.0, "intensified": 0.0}, "west": {"avg": 0.0, "maj": 0.0, "intensified": 0.0}}, "judgements": {"russia": [0.0, 0.0, 0.0, 0.0, 0.0], "ukraine": [0.0, 0.0, 0.0, 0.0, 0.0], "west": [0.0, 0.0, 0.0, 0.0, 0.0]}, "cw_origins": ["VEN", "VEN", "USA", "VEN", "COL"]}, "bias": {"score": {"pro-russia": {"avg": 0.9333333333333333, "maj": 1.0, "intensified": 1.0}, "pro-west": {"avg": 0.9333333333333333, "maj": 1.0, "intensified": 1.0}}, "judgements": {"pro-russia": [1.0, 1.0, 1.0, 1.0, 1.0, 1.0, 1.0, 1.0, 0.0, 1.0, 1.0, 1.0, 1.0, 1.0, 1.0], "pro-west": [1.0, 1.0, 1.0, 1.0, 1.0, 1.0, 1.0, 1.0, 0.0, 1.0, 1.0, 1.0, 1.0, 1.0, 1.0]}, "cw_origins": ["VEN", "USA", "VEN", "VEN", "VEN", "USA", "VEN", "VEN", "USA", "VEN", "USA", "VEN", "VEN", "VEN", "USA"]}}, {"article": "article_11", "id": "sent_95", "position_in_article": 4, "content": "Major Western countries, including the United States, denounced Putin\u2019s action to be nationalistic and threatened tougher sanctions against Russia, with some media reports heralding a new cold war era.", "subjectivity": {"score": {"avg": 0.6, "maj": 0.0, "intensified": 0.0}, "judgements": [0.0, 0.0, 1.0, 0.0, 2.0], "cw_origins": ["VEN", "VEN", "USA", "VEN", "TUR"]}, "hidden_assumptions": {"score": {"avg": 0.6, "maj": 0.0, "intensified": 0.0}, "judgements": [0.0, 0.0, 0.0, 1.0, 2.0], "cw_origins": ["USA", "USA", "USA", "BIH", "EGY"]}, "framing": {"score": {"russia": {"avg": 0.0, "maj": 0.0, "intensified": 0.0}, "ukraine": {"avg": 0.0, "maj": 0.0, "intensified": 0.0}, "west": {"avg": 0.0, "maj": 0.0, "intensified": 0.0}}, "judgements": {"russia": [0.0, 0.0, 0.0, 0.0, 0.0], "ukraine": [0.0, 0.0, 0.0, 0.0, 0.0], "west": [0.0, 0.0, 0.0, 0.0, 0.0]}, "cw_origins": ["VEN", "VEN", "USA", "VEN", "COL"]}, "bias": {"score": {"pro-russia": {"avg": 0.9333333333333333, "maj": 1.0, "intensified": 1.0}, "pro-west": {"avg": 0.9333333333333333, "maj": 1.0, "intensified": 1.0}}, "judgements": {"pro-russia": [1.0, 1.0, 1.0, 1.0, 1.0, 1.0, 1.0, 1.0, 0.0, 1.0, 1.0, 1.0, 1.0, 1.0, 1.0], "pro-west": [1.0, 1.0, 1.0, 1.0, 1.0, 1.0, 1.0, 1.0, 0.0, 1.0, 1.0, 1.0, 1.0, 1.0, 1.0]}, "cw_origins": ["VEN", "USA", "VEN", "VEN", "VEN", "USA", "VEN", "VEN", "USA", "VEN", "USA", "VEN", "VEN", "VEN", "USA"]}}, {"article": "article_11", "id": "sent_96", "position_in_article": 5, "content": "Joining such critical voices, South Korea\u2019s Ministry of Foreign Affairs voiced concerns over Russia\u2019s takeover of Crimea.", "subjectivity": {"score": {"avg": 0.6, "maj": 0.0, "intensified": 0.0}, "judgements": [0.0, 0.0, 1.0, 0.0, 2.0], "cw_origins": ["VEN", "VEN", "USA", "VEN", "TUR"]}, "hidden_assumptions": {"score": {"avg": 0.6, "maj": 0.0, "intensified": 0.0}, "judgements": [0.0, 0.0, 0.0, 1.0, 2.0], "cw_origins": ["USA", "USA", "USA", "BIH", "EGY"]}, "framing": {"score": {"russia": {"avg": 0.0, "maj": 0.0, "intensified": 0.0}, "ukraine": {"avg": 0.0, "maj": 0.0, "intensified": 0.0}, "west": {"avg": 0.0, "maj": 0.0, "intensified": 0.0}}, "judgements": {"russia": [0.0, 0.0, 0.0, 0.0, 0.0], "ukraine": [0.0, 0.0, 0.0, 0.0, 0.0], "west": [0.0, 0.0, 0.0, 0.0, 0.0]}, "cw_origins": ["VEN", "VEN", "USA", "VEN", "COL"]}, "bias": {"score": {"pro-russia": {"avg": 0.9333333333333333, "maj": 1.0, "intensified": 1.0}, "pro-west": {"avg": 0.9333333333333333, "maj": 1.0, "intensified": 1.0}}, "judgements": {"pro-russia": [1.0, 1.0, 1.0, 1.0, 1.0, 1.0, 1.0, 1.0, 0.0, 1.0, 1.0, 1.0, 1.0, 1.0, 1.0], "pro-west": [1.0, 1.0, 1.0, 1.0, 1.0, 1.0, 1.0, 1.0, 0.0, 1.0, 1.0, 1.0, 1.0, 1.0, 1.0]}, "cw_origins": ["VEN", "USA", "VEN", "VEN", "VEN", "USA", "VEN", "VEN", "USA", "VEN", "USA", "VEN", "VEN", "VEN", "USA"]}}, {"article": "article_11", "id": "sent_97", "position_in_article": 6, "content": "\u201cThe sovereignty, territorial right and independence of Ukraine must necessarily be respected,\u201d the ministry said in statement.", "subjectivity": {"score": {"avg": 0.4, "maj": 0.0, "intensified": 0.0}, "judgements": [0.0, 0.0, 1.0, 0.0, 1.0], "cw_origins": ["VEN", "VEN", "USA", "VEN", "TUR"]}, "hidden_assumptions": {"score": {"avg": 0.6, "maj": 0.0, "intensified": 0.0}, "judgements": [0.0, 0.0, 0.0, 1.0, 2.0], "cw_origins": ["USA", "USA", "USA", "BIH", "EGY"]}, "framing": {"score": {"russia": {"avg": 0.0, "maj": 0.0, "intensified": 0.0}, "ukraine": {"avg": 0.0, "maj": 0.0, "intensified": 0.0}, "west": {"avg": 0.0, "maj": 0.0, "intensified": 0.0}}, "judgements": {"russia": [0.0, 0.0, 0.0, 0.0, 0.0], "ukraine": [0.0, 0.0, 0.0, 0.0, 0.0], "west": [0.0, 0.0, 0.0, 0.0, 0.0]}, "cw_origins": ["VEN", "VEN", "USA", "VEN", "COL"]}, "bias": {"score": {"pro-russia": {"avg": 0.9333333333333333, "maj": 1.0, "intensified": 1.0}, "pro-west": {"avg": 0.9333333333333333, "maj": 1.0, "intensified": 1.0}}, "judgements": {"pro-russia": [1.0, 1.0, 1.0, 1.0, 1.0, 1.0, 1.0, 1.0, 0.0, 1.0, 1.0, 1.0, 1.0, 1.0, 1.0], "pro-west": [1.0, 1.0, 1.0, 1.0, 1.0, 1.0, 1.0, 1.0, 0.0, 1.0, 1.0, 1.0, 1.0, 1.0, 1.0]}, "cw_origins": ["VEN", "USA", "VEN", "VEN", "VEN", "USA", "VEN", "VEN", "USA", "VEN", "USA", "VEN", "VEN", "VEN", "USA"]}}, {"article": "article_11", "id": "sent_98", "position_in_article": 7, "content": "\u201cOur government cannot recognize the (recent) referendum on Crimean people and Russia\u2019s (subsequent) annexation of Crimea.\u201d ", "subjectivity": {"score": {"avg": 0.4, "maj": 0.0, "intensified": 0.0}, "judgements": [0.0, 0.0, 1.0, 0.0, 1.0], "cw_origins": ["VEN", "VEN", "USA", "VEN", "TUR"]}, "hidden_assumptions": {"score": {"avg": 0.6, "maj": 0.0, "intensified": 0.0}, "judgements": [0.0, 0.0, 0.0, 1.0, 2.0], "cw_origins": ["USA", "USA", "USA", "BIH", "EGY"]}, "framing": {"score": {"russia": {"avg": 0.0, "maj": 0.0, "intensified": 0.0}, "ukraine": {"avg": 0.0, "maj": 0.0, "intensified": 0.0}, "west": {"avg": 0.0, "maj": 0.0, "intensified": 0.0}}, "judgements": {"russia": [0.0, 0.0, 0.0, 0.0, 0.0], "ukraine": [0.0, 0.0, 0.0, 0.0, 0.0], "west": [0.0, 0.0, 0.0, 0.0, 0.0]}, "cw_origins": ["VEN", "VEN", "USA", "VEN", "COL"]}, "bias": {"score": {"pro-russia": {"avg": 0.9333333333333333, "maj": 1.0, "intensified": 1.0}, "pro-west": {"avg": 0.9333333333333333, "maj": 1.0, "intensified": 1.0}}, "judgements": {"pro-russia": [1.0, 1.0, 1.0, 1.0, 1.0, 1.0, 1.0, 1.0, 0.0, 1.0, 1.0, 1.0, 1.0, 1.0, 1.0], "pro-west": [1.0, 1.0, 1.0, 1.0, 1.0, 1.0, 1.0, 1.0, 0.0, 1.0, 1.0, 1.0, 1.0, 1.0, 1.0]}, "cw_origins": ["VEN", "USA", "VEN", "VEN", "VEN", "USA", "VEN", "VEN", "USA", "VEN", "USA", "VEN", "VEN", "VEN", "USA"]}}, {"article": "article_11", "id": "sent_99", "position_in_article": 8, "content": "Russia announced that more than 90 percent of Crimean residents approved Russia\u2019s takeover of the region in a referendum last week, but allegations of a possible fraud have been raised.", "subjectivity": {"score": {"avg": 0.4, "maj": 0.0, "intensified": 0.0}, "judgements": [0.0, 0.0, 1.0, 0.0, 1.0], "cw_origins": ["VEN", "VEN", "USA", "VEN", "TUR"]}, "hidden_assumptions": {"score": {"avg": 0.6, "maj": 0.0, "intensified": 0.0}, "judgements": [0.0, 0.0, 0.0, 1.0, 2.0], "cw_origins": ["USA", "USA", "USA", "BIH", "EGY"]}, "framing": {"score": {"russia": {"avg": 0.0, "maj": 0.0, "intensified": 0.0}, "ukraine": {"avg": 0.0, "maj": 0.0, "intensified": 0.0}, "west": {"avg": 0.0, "maj": 0.0, "intensified": 0.0}}, "judgements": {"russia": [0.0, 0.0, 0.0, 0.0, 0.0], "ukraine": [0.0, 0.0, 0.0, 0.0, 0.0], "west": [0.0, 0.0, 0.0, 0.0, 0.0]}, "cw_origins": ["VEN", "VEN", "USA", "VEN", "COL"]}, "bias": {"score": {"pro-russia": {"avg": 0.9333333333333333, "maj": 1.0, "intensified": 1.0}, "pro-west": {"avg": 0.9333333333333333, "maj": 1.0, "intensified": 1.0}}, "judgements": {"pro-russia": [1.0, 1.0, 1.0, 1.0, 1.0, 1.0, 1.0, 1.0, 0.0, 1.0, 1.0, 1.0, 1.0, 1.0, 1.0], "pro-west": [1.0, 1.0, 1.0, 1.0, 1.0, 1.0, 1.0, 1.0, 0.0, 1.0, 1.0, 1.0, 1.0, 1.0, 1.0]}, "cw_origins": ["VEN", "USA", "VEN", "VEN", "VEN", "USA", "VEN", "VEN", "USA", "VEN", "USA", "VEN", "VEN", "VEN", "USA"]}}], "subjectivity": {"avg": 0.0, "maj": 0.0, "intensified": 0.0}, "hidden_assumptions": {"avg": 0.0, "maj": 0.0, "intensified": 0.0}, "framing": {"russia": {"pos_sent": {"avg": 0.0, "maj": 0.0, "intensified": 0.0}, "neutral_sent": {"avg": 1.0, "maj": 1.0, "intensified": 1.0}, "neg_sent": {"avg": 0.0, "maj": 0.0, "intensified": 0.0}}, "ukraine": {"pos_sent": {"avg": 0.0, "maj": 0.0, "intensified": 0.0}, "neutral_sent": {"avg": 1.0, "maj": 1.0, "intensified": 1.0}, "neg_sent": {"avg": 0.0, "maj": 0.0, "intensified": 0.0}}, "west": {"pos_sent": {"avg": 0.0, "maj": 0.0, "intensified": 0.0}, "neutral_sent": {"avg": 1.0, "maj": 1.0, "intensified": 1.0}, "neg_sent": {"avg": 0.0, "maj": 0.0, "intensified": 0.0}}}, "bias": {"pro-russia": {"avg": 0.0, "maj": 0.0, "intensified": 0.0}, "pro-west": {"avg": 0.0, "maj": 0.0, "intensified": 0.0}}}